<?xml version="1.0" encoding="utf-8"?>
<root>
	<plugin>
		<caption>环境信息</caption>
		<show>Y</show>
		<show-order>0</show-order>
		<show-level>0</show-level>
		<datasrc>data_src_null</datasrc>
	</plugin>
	<plugin>
		<caption>中间件信息</caption>
		<show>Y</show>
		<show-order>10</show-order>
		<show-level>1</show-level>
		<datasrc>npr.mwinfo</datasrc>
		<format>table</format>
		<impl-class>uap.ps.itm.npr.service.plugin.MWSummaryPluginImpl</impl-class>
	</plugin>
	<plugin>
		<caption>数据库信息</caption>
		<show>Y</show>
		<show-order>20</show-order>
		<show-level>1</show-level>
		<datasrc>npr.dbinfo</datasrc>
		<format>table</format>
		<impl-class>uap.ps.itm.npr.service.plugin.DBSummaryPluginImpl</impl-class>
	</plugin>
	<plugin>
		<caption>Summary</caption>
		<show>Y</show>
		<show-order>25</show-order>
		<show-level>0</show-level>
		<datasrc>data_src_null</datasrc>
	</plugin>
	<plugin>
		<caption>集群吞吐量</caption>
		<show>Y</show>
		<show-order>30</show-order>
		<show-level>1</show-level>
		<datasrc>nmc.mw</datasrc>
		<format>table</format>
		<para1>cluster</para1>
		<impl-class>uap.ps.itm.npr.service.plugin.ServersThroughputPluginImpl</impl-class>
	</plugin>
	<plugin>
		<caption>Master吞吐量</caption>
		<show>Y</show>
		<show-order>40</show-order>
		<show-level>1</show-level>
		<datasrc>nmc.mw</datasrc>
		<format>table</format>
		<para1>master</para1>
		<impl-class>uap.ps.itm.npr.service.plugin.ThroughputPluginImpl</impl-class>
	</plugin>
	<plugin>
		<caption>Server吞吐量</caption>
		<show>Y</show>
		<show-order>50</show-order>
		<show-level>1</show-level>
		<datasrc>nmc.mw</datasrc>
		<format>table</format>
		<para1>servers</para1>
		<impl-class>uap.ps.itm.npr.service.plugin.ServersThroughputPluginImpl</impl-class>
	</plugin>
	<plugin>
		<caption>中间件CPU时间</caption>
		<show>Y</show>
		<show-order>60</show-order>
		<show-level>1</show-level>
		<datasrc>uap.ps.itm.mw</datasrc>
		<format>table</format>
		<impl-class>uap.ps.itm.npr.service.plugin.MWCpuTimePluginImpl</impl-class>
	</plugin>
	<plugin>
		<caption>网络流量</caption>
		<show>Y</show>
		<show-order>70</show-order>
		<show-level>1</show-level>
		<datasrc>nc.mw</datasrc>
		<format>table</format>
		<impl-class>uap.ps.itm.npr.service.plugin.NetworkTrafficPluginImpl</impl-class>
	</plugin>
	<plugin>
		<caption>数据库负载波动图</caption>
		<show>Y</show>
		<show-order>80</show-order>
		<show-level>1</show-level>
		<datasrc>nmc.db</datasrc>
		<format>chart</format>
		<chart-type>LineChart</chart-type>
		<chart-title>Database workload</chart-title>
		<chart-high>480</chart-high>
		<line-name>Active sessions</line-name>
		<x-field>ts</x-field>
		<sys-interval>5</sys-interval>
		<!--统计时格以秒为单位，5秒的倍数，最小为5秒-->
		<time-bucket>7200</time-bucket>
		<y-field>activesessions</y-field>
		<y-tital>Session count</y-tital>
		<impl-class>uap.ps.itm.npr.service.plugin.DatabaseWorkLoadChartImpl</impl-class>
	</plugin>
	<plugin>
		<caption>SQL统计</caption>
		<show>Y</show>
		<show-order>85</show-order>
		<show-level>1</show-level>
		<datasrc>nc.mw</datasrc>
		<format>table</format>
		<impl-class>uap.ps.itm.npr.service.plugin.SQLExecuteSummaryImpl</impl-class>
	</plugin>
		<plugin>
		<caption>系统监控</caption>
		<show>Y</show>
		<show-order>86</show-order>
		<show-level>1</show-level>
		<datasrc>nmc.systemmonitor</datasrc>
		<format>chart</format>
		<chart-type>LineChart</chart-type>
		<chart-title>System monitor</chart-title>
		<chart-width>2048</chart-width>
		<chart-high>512</chart-high>
		<x-field>ts</x-field>
		<sys-interval>5</sys-interval>
		<!--统计时格以秒为单位，5秒的倍数，最小为5秒-->
		<time-bucket>3600</time-bucket>
		<impl-class>uap.ps.itm.npr.service.plugin.SystemMonitorPluginImpl</impl-class>
	</plugin>
	<plugin>
		<caption>在线用户统计信息</caption>
		<show>Y</show>
		<show-order>90</show-order>
		<show-level>0</show-level>
		<datasrc>data_src_null</datasrc>
	</plugin>
	<plugin>
		<caption>在线用户数波动图</caption>
		<show>Y</show>
		<show-order>100</show-order>
		<show-level>1</show-level>
		<datasrc>nmc.onlineuser</datasrc>
		<format>chart</format>
		<chart-type>LineChart</chart-type>
		<chart-title>Online user quantity</chart-title>
		<chart-width>1024</chart-width>
		<chart-high>480</chart-high>
		<line-name>Quantity</line-name>
		<x-field>ts</x-field>
		<sys-interval>120</sys-interval>
		<!--统计时格以秒为单位，120秒的倍数，最小为120秒-->
		<time-bucket>7200</time-bucket>
		<y-field>usercount</y-field>
		<y-tital>User count</y-tital>
		<impl-class>uap.ps.itm.npr.service.plugin.OnlineUserChartImpl</impl-class>
	</plugin>
	<plugin>
		<caption>在线用户数统计表</caption>
		<show>Y</show>
		<show-order>110</show-order>
		<show-level>1</show-level>
		<datasrc>nmc.onlineuser</datasrc>
		<format>table</format>
		<impl-class>uap.ps.itm.npr.service.plugin.OnlineUserTableImpl</impl-class>
	</plugin>
	<plugin>
		<caption>TopN统计</caption>
		<show>Y</show>
		<show-order>120</show-order>
		<show-level>0</show-level>
		<datasrc>data_src_null</datasrc>
	</plugin>
	<plugin>
		<caption>最耗时的远程调用TopN</caption>
		<show>Y</show>
		<show-order>130</show-order>
		<show-level>1</show-level>
		<datasrc>nc.mw</datasrc>
		<format>table</format>
		<filter-file>最耗时的远程调用TopN</filter-file>
		<impl-class>uap.ps.itm.npr.service.plugin.RemoteCallCostTimeTop10</impl-class>
	</plugin>
	<plugin>
		<caption>网络上行流量最大的远程调用TopN</caption>
		<show>Y</show>
		<show-order>140</show-order>
		<show-level>1</show-level>
		<datasrc>nc.mw</datasrc>
		<format>table</format>		
		<filter-file>网络上行流量最大的远程调用TopN</filter-file>
		<impl-class>uap.ps.itm.npr.service.plugin.RemoteCallWriteTrafficTop10</impl-class>
	</plugin>
	<plugin>
		<caption>网络下行流量最大的远程调用TopN</caption>
		<show>Y</show>
		<show-order>150</show-order>
		<show-level>1</show-level>
		<datasrc>nc.mw</datasrc>
		<format>table</format>
		<filter-file>网络下行流量最大的远程调用TopN</filter-file>
		<impl-class>uap.ps.itm.npr.service.plugin.RemoteCallReadTrafficTop10</impl-class>
	</plugin>
	<plugin>
		<caption>读取结果集最多的远程调用TopN</caption>
		<show>Y</show>
		<show-order>160</show-order>
		<show-level>1</show-level>
		<datasrc>nc.mw</datasrc>
		<format>table</format>
		<filter-file>读取结果集最多的远程调用TopN</filter-file>
		<impl-class>uap.ps.itm.npr.service.plugin.RemoteCallResultTop10</impl-class>
	</plugin>
	<!--
	<plugin>
		<caption>执行次数最多的操作TopN</caption>
		<show>Y</show>
		<show-order>170</show-order>
		<show-level>1</show-level>
		<datasrc>nc.mw</datasrc>
		<format>table</format>
		<impl-class>nc.npr.service.plugin.BusyBusiActionTop10</impl-class>
	</plugin>
	-->
	<plugin>
		<caption>最耗时的SQLTopN</caption>
		<show>Y</show>
		<show-order>180</show-order>
		<show-level>1</show-level>
		<datasrc>nc.warningsql</datasrc>
		<format>table</format>
		<filter-file>最耗时的SQLTopN</filter-file>
		<impl-class>uap.ps.itm.npr.service.plugin.SQLCostTimeTop10</impl-class>
	</plugin>
	<plugin>
		<caption>结果集最多的SQLTopN</caption>
		<show>Y</show>
		<show-order>190</show-order>
		<show-level>1</show-level>
		<datasrc>nc.warningsql</datasrc>
		<format>table</format>
		<filter-file>结果集最多的SQLTopN</filter-file>
		<impl-class>uap.ps.itm.npr.service.plugin.SQLResultTop10</impl-class>
	</plugin>
	<plugin>
		<caption>SQL数量最多的远程调用TopN</caption>
		<show>Y</show>
		<show-order>200</show-order>
		<show-level>1</show-level>
		<datasrc>nc.mw</datasrc>
		<format>table</format>
		<filter-file>SQL数量最多的远程调用TopN</filter-file>
		<impl-class>uap.ps.itm.npr.service.plugin.RemoteCallSQLNumsTop10</impl-class>
	</plugin>
	<plugin>
		<caption>Master服务使用频率最高的远程调用TopN</caption>
		<show>Y</show>
		<show-order>210</show-order>
		<show-level>1</show-level>
		<datasrc>nc.mw</datasrc>
		<format>table</format>
		<filter-file>对Master请求最多的远程调用TopN</filter-file>
		<impl-class>uap.ps.itm.npr.service.plugin.RequestMasterTop10</impl-class>
	</plugin>
	<plugin>
		<caption>对Master请求最多的远程调用TopN</caption>
		<show>Y</show>
		<show-order>210</show-order>
		<show-level>1</show-level>
		<datasrc>nc.mw</datasrc>
		<format>table</format>
		<filter-file>对Master请求最多的远程调用TopN</filter-file>
		<impl-class>uap.ps.itm.npr.service.plugin.CallMasterNumsTop10</impl-class>
	</plugin>
	<plugin>
		<caption>数据库连接次数最多的远程调用TopN</caption>
		<show>Y</show>
		<show-order>210</show-order>
		<show-level>1</show-level>
		<datasrc>nc.mw</datasrc>
		<format>table</format>
		<filter-file>数据库连接次数最多的远程调用TopN</filter-file>
		<impl-class>uap.ps.itm.npr.service.plugin.CallDbNumsTop10</impl-class>
	</plugin>
	<plugin>
		<caption>错误信息统计</caption>
		<show>Y</show>
		<show-order>220</show-order>
		<show-level>0</show-level>
		<datasrc>data_src_null</datasrc>
	</plugin>
	<plugin>
		<caption>连接泄露的远程调用统计</caption>
		<show>Y</show>
		<show-order>230</show-order>
		<show-level>1</show-level>
		<datasrc>nc.mw</datasrc>
		<format>table</format>
		<filter-file>连接泄露的远程调用统计</filter-file>
		<impl-class>uap.ps.itm.npr.service.plugin.RemoteCallConnNotClosePluginImpl</impl-class>
	</plugin>
	<plugin>
		<caption>怀疑远程调用次数超标的操作</caption>
		<show>Y</show>
		<show-order>240</show-order>
		<show-level>1</show-level>
		<datasrc>nc.mw</datasrc>
		<format>table</format>
		<filter-file>怀疑远程调用次数超标的操作</filter-file>
		<impl-class>uap.ps.itm.npr.service.plugin.RemoteCallTimesOverLimit</impl-class>
	</plugin>
	<plugin>
		<caption>SQL数量超标的远程调用统计</caption>
		<show>Y</show>
		<show-order>250</show-order>
		<show-level>1</show-level>
		<datasrc>nc.mw</datasrc>
		<format>table</format>
		<filter-file>SQL数量超标的远程调用统计</filter-file>
		<impl-class>uap.ps.itm.npr.service.plugin.RemoteCallSQLTimesOverLimit</impl-class>
	</plugin>
	<plugin>
		<caption>上行或下行流量超过1M的远程调用统计</caption>
		<show>Y</show>
		<show-order>260</show-order>
		<show-level>1</show-level>
		<datasrc>nc.mw</datasrc>
		<format>table</format>
		<filter-file>上行或下行流量超过1M的远程调用统计</filter-file>
		<impl-class>uap.ps.itm.npr.service.plugin.ReadOrWriteOver1MImpl</impl-class>
	</plugin>
	<plugin>
		<caption>中间件运行情况统计</caption>
		<show>Y</show>
		<show-order>270</show-order>
		<show-level>0</show-level>
		<datasrc>data_src_null</datasrc>
	</plugin>
	<plugin>
		<caption>中间件JVM堆使用情况</caption>
		<show>Y</show>
		<show-order>280</show-order>
		<show-level>1</show-level>
		<datasrc>nmc.mw</datasrc>
		<format>chart</format>
		<chart-type>LineChart</chart-type>
		<chart-title>JVM heap used</chart-title>
		<chart-width>2048</chart-width>
		<chart-high>512</chart-high>
		<x-field>ts</x-field>
		<sys-interval>10</sys-interval>
		<!--统计时格以秒为单位，logDuration的倍数(默认为10秒)，最小为5秒-->
		<time-bucket>3600</time-bucket>
		<y-field>used</y-field>
		<y-tital>Heap used(MB)</y-tital>
		<impl-class>uap.ps.itm.npr.service.plugin.JvmMemoryChartImpl</impl-class>
	</plugin>
	<plugin>
		<caption>中间件JVM响应时间</caption>
		<show>Y</show>
		<show-order>290</show-order>
		<show-level>1</show-level>
		<datasrc>nmc.mw</datasrc>
		<format>chart</format>
		<chart-type>LineChart</chart-type>
		<chart-title>JVM response time</chart-title>
		<chart-width>2048</chart-width>
		<chart-high>512</chart-high>
		<x-field>ts</x-field>
		<sys-interval>5</sys-interval>
		<!--统计时格以秒为单位，5秒的倍数，最小为5秒-->
		<time-bucket>3600</time-bucket>
		<y-field>cost</y-field>
		<y-tital>Response time(second)</y-tital>
		<impl-class>uap.ps.itm.npr.service.plugin.JvmRespCostChartImpl</impl-class>
	</plugin>
	<plugin>
		<caption>中间件JVM吞吐量</caption>
		<show>Y</show>
		<show-order>300</show-order>
		<show-level>1</show-level>
		<datasrc>nmc.mw</datasrc>
		<format>chart</format>
		<chart-type>LineChart</chart-type>
		<chart-title>JVM throughput</chart-title>
		<chart-width>2048</chart-width>
		<chart-high>512</chart-high>
		<x-field>ts</x-field>
		<sys-interval>5</sys-interval>
		<!--统计时格以秒为单位，5秒的倍数，最小为5秒-->
		<time-bucket>3600</time-bucket>
		<y-field>throughput</y-field>
		<y-tital>Throughput</y-tital>
		<impl-class>uap.ps.itm.npr.service.plugin.JvmThroughputChartImpl</impl-class>
	</plugin>
	<plugin>
		<caption>中间件JVM Web线程数</caption>
		<show>Y</show>
		<show-order>310</show-order>
		<show-level>1</show-level>
		<datasrc>nmc.mw</datasrc>
		<format>chart</format>
		<chart-type>LineChart</chart-type>
		<chart-title>JVM web threads</chart-title>
		<chart-width>2048</chart-width>
		<chart-high>512</chart-high>
		<x-field>ts</x-field>
		<sys-interval>5</sys-interval>
		<!--统计时格以秒为单位，5秒的倍数，最小为5秒-->
		<time-bucket>3600</time-bucket>
		<y-field>webthread</y-field>
		<y-tital>Threads</y-tital>
		<impl-class>uap.ps.itm.npr.service.plugin.JvmWebThreadChartImpl</impl-class>
	</plugin>
	
	<plugin>
		<caption>消息快照</caption>
		<show>Y</show>
		<show-order>320</show-order>
		<show-level>1</show-level>
		<datasrc>nmc.snapshot</datasrc>
		<format>snapshot</format>
		<link-filed>快照详细</link-filed>
		<impl-class>uap.ps.itm.npr.service.plugin.MsgSnapshotPlugImpl</impl-class>
	</plugin>
</root>